teo-0.3.9.dist-info/METADATA
teo-0.3.9.dist-info/WHEEL
teo-0.3.9.dist-info/entry_points.txt
teo-0.3.9.dist-info/licenses/LICENSE
teo/test/__init__.py
teo/test/matchers.py
teo/__init__.pyi
teo/__init__.py
teo/annotations/__init__.py
teo/cli.py
teo/py.typed
teo/teo.cpython-313-darwin.so
teo-0.3.9.dist-info/RECORD
